google/cloud/recommender/__init__.py
google/cloud/recommender/gapic_version.py
google/cloud/recommender/py.typed
google/cloud/recommender_v1/__init__.py
google/cloud/recommender_v1/gapic_metadata.json
google/cloud/recommender_v1/gapic_version.py
google/cloud/recommender_v1/py.typed
google/cloud/recommender_v1/services/__init__.py
google/cloud/recommender_v1/services/recommender/__init__.py
google/cloud/recommender_v1/services/recommender/async_client.py
google/cloud/recommender_v1/services/recommender/client.py
google/cloud/recommender_v1/services/recommender/pagers.py
google/cloud/recommender_v1/services/recommender/transports/__init__.py
google/cloud/recommender_v1/services/recommender/transports/base.py
google/cloud/recommender_v1/services/recommender/transports/grpc.py
google/cloud/recommender_v1/services/recommender/transports/grpc_asyncio.py
google/cloud/recommender_v1/services/recommender/transports/rest.py
google/cloud/recommender_v1/services/recommender/transports/rest_base.py
google/cloud/recommender_v1/types/__init__.py
google/cloud/recommender_v1/types/insight.py
google/cloud/recommender_v1/types/insight_type_config.py
google/cloud/recommender_v1/types/recommendation.py
google/cloud/recommender_v1/types/recommender_config.py
google/cloud/recommender_v1/types/recommender_service.py
google/cloud/recommender_v1beta1/__init__.py
google/cloud/recommender_v1beta1/gapic_metadata.json
google/cloud/recommender_v1beta1/gapic_version.py
google/cloud/recommender_v1beta1/py.typed
google/cloud/recommender_v1beta1/services/__init__.py
google/cloud/recommender_v1beta1/services/recommender/__init__.py
google/cloud/recommender_v1beta1/services/recommender/async_client.py
google/cloud/recommender_v1beta1/services/recommender/client.py
google/cloud/recommender_v1beta1/services/recommender/pagers.py
google/cloud/recommender_v1beta1/services/recommender/transports/__init__.py
google/cloud/recommender_v1beta1/services/recommender/transports/base.py
google_cloud_recommender-2.19.0.dist-info/licenses/LICENSE
google_cloud_recommender-2.19.0.dist-info/METADATA
google_cloud_recommender-2.19.0.dist-info/WHEEL
google_cloud_recommender-2.19.0.dist-info/top_level.txt
google_cloud_recommender-2.19.0.dist-info/RECORD
